jacobsjsondoc/__init__.py
jacobsjsondoc/_version.py
jacobsjsondoc/document.py
jacobsjsondoc/loader.py
jacobsjsondoc/options.py
jacobsjsondoc/parser.py
jacobsjsondoc/reference.py
jacobsjsondoc/util.py
tests/__init__.py
tests/context.py
tests/test_document.py
tests/test_imports.py
tests/test_parse.py
tests/test_quick_parse.py
tests/test_reference.py
tests/test_types.py
tests/test_util.py
jacobs_json_doc-0.16.3.dist-info/LICENSE
jacobs_json_doc-0.16.3.dist-info/METADATA
jacobs_json_doc-0.16.3.dist-info/WHEEL
jacobs_json_doc-0.16.3.dist-info/top_level.txt
jacobs_json_doc-0.16.3.dist-info/RECORD
