Metadata-Version: 2.1
Name: jacobs-json-doc
Version: 0.16.3
Summary: A JSON/YAML loader
Home-page: https://github.com/pearmaster/jacobs-json-doc
Author: Jacob Brunson
Author-email: pypi@jacobbrunson.com
License: GPLv2
Keywords: conversion
Platform: UNKNOWN
Classifier: Programming Language :: Python :: 3
Requires-Python: >=3.7
License-File: LICENSE
Requires-Dist: ruamel.yaml (==0.17.17)
